Metadata-Version: 2.1
Name: FruitScript
Version: 1.0.0
Summary: FruitScript is a module with multiple purposes, file management, on the spot being able to use things and maybe a bunch of useless shit that you don't need, lol. 😀
Home-page: https://github.com/ItzBlueBerries/FruitScript
Author: Fruitsy
License: UNKNOWN
Project-URL: Bug Tracker, https://github.com/ItzBlueBerries/FruitScript/issues
Project-URL: Pull Requests, https://github.com/ItzBlueBerries/FruitScript/pulls
Project-URL: Forks, https://github.com/ItzBlueBerries/FruitScript/network/members
Platform: UNKNOWN
Classifier: Programming Language :: Python :: 3
Classifier: License :: OSI Approved :: MIT License
Classifier: Operating System :: OS Independent
Requires-Python: >=3.6
